MANIFEST.in
README.txt
setup.cfg
setup.py
eg/__init__.py
eg.theme.egg-info/PKG-INFO
eg.theme.egg-info/SOURCES.txt
eg.theme.egg-info/dependency_links.txt
eg.theme.egg-info/entry_points.txt
eg.theme.egg-info/namespace_packages.txt
eg.theme.egg-info/not-zip-safe
eg.theme.egg-info/paster_plugins.txt
eg.theme.egg-info/requires.txt
eg.theme.egg-info/top_level.txt
eg/theme/__init__.py
eg/theme/configure.zcml
eg/theme/extender.py
eg/theme/profiles.zcml
eg/theme/setuphandlers.py
eg/theme/skins.zcml
eg/theme/tests.py
eg/theme/version.txt
eg/theme/vocabularies.py
eg/theme/browser/__init__.py
eg/theme/browser/__init__.pyo
eg/theme/browser/configure.zcml
eg/theme/browser/egosearch.py
eg/theme/browser/interfaces.py
eg/theme/browser/navigation.py
eg/theme/browser/navigation_org.py
eg/theme/browser/navtree_org.py
eg/theme/browser/path_bar_ego.pt
eg/theme/browser/viewlet.pt
eg/theme/browser/viewlets.py
eg/theme/browser/images/README.txt
eg/theme/browser/stylesheets/README.txt
eg/theme/browser/stylesheets/main.css
eg/theme/browser/templates/navigation.pt
eg/theme/browser/templates/navigation_org.pt
eg/theme/browser/templates/navigation_recurse.pt
eg/theme/browser/templates/navigation_recurse_org.pt
eg/theme/i18n/eg.theme-de.po
eg/theme/i18n/eg.theme.pot
eg/theme/locales/README.txt
eg/theme/locales/eg.theme.pot
eg/theme/locales/de/LC_MESSAGES/eg.theme.mo
eg/theme/locales/de/LC_MESSAGES/eg.theme.po
eg/theme/locales/i18n/eg.theme-de.po
eg/theme/profiles/default/catalog.xml
eg/theme/profiles/default/cssregistry.xml
eg/theme/profiles/default/eg.theme_various.txt
eg/theme/profiles/default/eg_theme-default.txt
eg/theme/profiles/default/jsregistry.xml
eg/theme/profiles/default/metadata.xml
eg/theme/profiles/default/skins.xml
eg/theme/profiles/default/viewlets.xml
eg/theme/skins/eg_theme_custom_images/CONTENT.txt
eg/theme/skins/eg_theme_custom_templates/CONTENT.txt
eg/theme/skins/eg_theme_styles/CONTENT.txt
eg/theme/skins/eg_theme_styles/base_properties.props