Metadata-Version: 1.0
Name: eg.theme
Version: 1.06
Summary: An installable theme for Plone 3
Home-page: http://svn.plone.org/svn/collective/
Author: UNKNOWN
Author-email: UNKNOWN
License: GPL
Platform: UNKNOWN
Classifier: Framework :: Plone
Classifier: Programming Language :: Python
